{
  "stone-furnace": {
    "image": "stone-furnace.png",
    "name": "Stone Furnace",
    "type": "Furnace",
    "group": "Production",
    "id": "stone-furnace"
  },
   "transport-belt": {
    "image": "transport-belt.png",
    "name": "Basic Transport Belt",
    "type": "Belt",
    "group": "Production",
    "id": "basic-belt"
  },
  "fast-inserter": {
    "image": "fast-inserter.png",
    "name": "Fast Inserter",
    "type": "Inserter",
    "group": "Production",
    "id": "fast-inserter"
  },
  "wooden-chest": {
    "image": "wood-chest.png",
    "name": "Wooden Chest",
    "type": "Chest",
    "group": "Storage",
    "id": "wooden-chest"
  },
  "asm-1": {
    "image": "asm-1p.png",
    "name": "Assembly Machine 1",
    "type": "Assembly",
    "group": "Assembly",
    "id": "asm-1"
  },
  "steel-chest": {
    "image": "steel-chest.png",
    "name": "Steel Chest",
    "type": "Chest",
    "group": "Storage",
    "id": "steel-chest"
  },
  "wall": {
    "image": "wall.png",
    "name": "Stone Wall",
    "type": "Defence",
    "group": "Defence",
    "id": "stone-wall"
  }
}
